videoclusters/__init__.py
videoclusters/centroid_based/KMeans.py
videoclusters/centroid_based/__init__.py
videoclusters-0.0.4.dist-info/LICENSE.txt
videoclusters-0.0.4.dist-info/METADATA
videoclusters-0.0.4.dist-info/WHEEL
videoclusters-0.0.4.dist-info/top_level.txt
videoclusters-0.0.4.dist-info/RECORD
