Metadata-Version: 2.1
Name: videoclusters
Version: 0.0.4
Summary: Python library to perform clustering computations on GPU.
Home-page: https://github.com/medoedka/videoclusters
Author: Andrew Vas
Project-URL: Bug Tracker, https://github.com/medoedka/videoclusters/issues
Classifier: Programming Language :: Python :: 3
Classifier: License :: OSI Approved :: MIT License
Classifier: Operating System :: OS Independent
Requires-Python: >=3.7
License-File: LICENSE.txt
